Metadata-Version: 2.1
Name: datacleanerpandas
Version: 0.1.0
Summary: A package for handling various data preprocessing tasks
Home-page: https://github.com/baharkarakas/datacleanerpandas
Download-URL: https://github.com/baharkarakas/datacleanerpandas/archive/refs/tags/v0.1.0.tar.gz
Author: baharkarakas & AlperCna
Author-email: support@pandasdatacleaner.com
Classifier: Programming Language :: Python :: 3
Classifier: License :: OSI Approved :: MIT License
Classifier: Operating System :: OS Independent
Requires-Python: >=3.8
Requires-Dist: pandas
Requires-Dist: numpy
Requires-Dist: scikit-learn
Requires-Dist: nltk
Requires-Dist: category_encoders
